{"details":{"adult":false,"backdrop_path":"/1ygwQw1Jf8s9Q4fx2Rym7DccRBQ.jpg","created_by":[{"id":513378,"credit_id":"657850c7ec8a430137ffc7ba","name":"Elizabeth Meriwether","original_name":"Elizabeth Meriwether","gender":1,"profile_path":"/jWDH9pv8huDNFNhaasCAUzuTgVy.jpg"},{"id":1609700,"credit_id":"657850d72dc9dc0100cc2080","name":"Kim Rosenstock","original_name":"Kim Rosenstock","gender":1,"profile_path":"/prGRp5LUzNV8Gh7OvASAqH3KYkz.jpg"}],"episode_run_time":[],"first_air_date":"2025-04-04","genres":[{"id":18,"name":"Drama"},{"id":35,"name":"Comedy"}],"homepage":"https://www.fxnetworks.com/shows/dying-for-sex","id":241405,"in_production":false,"languages":["en"],"last_air_date":"2025-04-04","last_episode_to_air":{"id":5980988,"name":"It's Not That Serious","overview":"Molly reflects on her life.","vote_average":1,"vote_count":1,"air_date":"2025-04-04","episode_number":8,"episode_type":"finale","production_code":"","runtime":37,"season_number":1,"show_id":241405,"still_path":"/3Tmk1gQ30EsvjmUkmAjp7x0gQtd.jpg"},"name":"Dying for Sex","next_episode_to_air":null,"networks":[{"id":453,"logo_path":"/pqUTCleNUiTLAVlelGxUgWn1ELh.png","name":"Hulu","origin_country":"US"}],"number_of_episodes":8,"number_of_seasons":1,"origin_country":["US"],"original_language":"en","original_name":"Dying for Sex","overview":"After Molly Kochan receives a diagnosis of Stage IV metastatic breast cancer, she leaves her husband and explores the full breadth and complexity of her sexual desires for the first time in her life.","popularity":43.8505,"poster_path":"/xaKb3cTh8mT6fgLSXuqo4JoS0dU.jpg","production_companies":[{"id":236166,"logo_path":"/8rFlu5iytnjsciYXZDw90ktllCI.png","name":"20th Television","origin_country":"US"},{"id":158303,"logo_path":"/5moUKtjrLuFa27rh0WxHJgc9m9Q.png","name":"Wondery","origin_country":"US"},{"id":5536,"logo_path":null,"name":"Elizabeth Meriwether Pictures","origin_country":"US"},{"id":258550,"logo_path":null,"name":"Pasta with Sauce","origin_country":"US"}],"production_countries":[{"iso_3166_1":"US","name":"United States of America"}],"seasons":[{"air_date":"2025-04-04","episode_count":8,"id":369530,"name":"Miniseries","overview":"","poster_path":"/xaKb3cTh8mT6fgLSXuqo4JoS0dU.jpg","season_number":1,"vote_average":1.2}],"spoken_languages":[{"english_name":"English","iso_639_1":"en","name":"English"}],"status":"Ended","tagline":"Come as you are.","type":"Miniseries","vote_average":6,"vote_count":41},"ratings":{"descriptors":[],"iso_3166_1":"US","name":"United States of America","rating":"TV-MA"},"originCountry":[{"iso_3166_1":"US","english_name":"United States of America","native_name":"United States"}],"credits":{"cast":[{"adult":false,"gender":1,"id":1812,"known_for_department":"Acting","name":"Michelle Williams","original_name":"Michelle Williams","popularity":3.1418,"profile_path":"/mfgKyigaQLI0NtZsaJRVlbUiMdX.jpg","character":"Molly Kochan","credit_id":"657850efec8a4300aa6cd80d","order":0},{"adult":false,"gender":1,"id":213001,"known_for_department":"Acting","name":"Jenny Slate","original_name":"Jenny Slate","popularity":2.0765,"profile_path":"/iNpXig5Djkh5moYG4TCekIATs5B.jpg","character":"Nikki Boyer","credit_id":"65a82ea8cd2f0f0127bb0879","order":1},{"adult":false,"gender":2,"id":45405,"known_for_department":"Production","name":"Jay Duplass","original_name":"Jay Duplass","popularity":0.7136,"profile_path":"/zDaNqdtchFBGmT6yR6prTm0rd4V.jpg","character":"Steve","credit_id":"67ba3a0b55e3994bbd466c26","order":2},{"adult":false,"gender":2,"id":51997,"known_for_department":"Acting","name":"Kelvin Yu","original_name":"Kelvin Yu","popularity":0.2362,"profile_path":"/47m8mUsuNIEyLb3KeDpryyvK0LI.jpg","character":"Noah","credit_id":"67ba3a1c55e3994bbd466c3c","order":3},{"adult":false,"gender":2,"id":33533,"known_for_department":"Acting","name":"David Rasche","original_name":"David Rasche","popularity":1.3376,"profile_path":"/bWPhfa4m8pXVneP1gf37xvuMUCA.jpg","character":"Dr. Pankowitz","credit_id":"67ba3a2755e3994bbd466c42","order":4},{"adult":false,"gender":3,"id":3400502,"known_for_department":"Acting","name":"Esco Jouléy","original_name":"Esco Jouléy","popularity":0.8215,"profile_path":"/fmOilIpT78npW7zajQjOh5amLA8.jpg","character":"Sonya","credit_id":"67ba3a32effeb96e9e0a9125","order":5},{"adult":false,"gender":2,"id":1091324,"known_for_department":"Acting","name":"Rob Delaney","original_name":"Rob Delaney","popularity":0.7485,"profile_path":"/xirfT1znRkkughLiPemKu3NhkKQ.jpg","character":"Neighbor Guy","credit_id":"67ba3a41b7c35459adbec5f4","order":6},{"adult":false,"gender":1,"id":5606,"known_for_department":"Acting","name":"Sissy Spacek","original_name":"Sissy Spacek","popularity":1.3474,"profile_path":"/xAxenjxjLNQFq4v1ccS2to3Mnoq.jpg","character":"Gail","credit_id":"67ba3a5ca23929ac28beba9b","order":7}],"crew":[{"adult":false,"gender":1,"id":513378,"known_for_department":"Writing","name":"Elizabeth Meriwether","original_name":"Elizabeth Meriwether","popularity":0.4079,"profile_path":"/jWDH9pv8huDNFNhaasCAUzuTgVy.jpg","credit_id":"6578510520ecaf00e3924936","department":"Production","job":"Executive Producer"},{"adult":false,"gender":1,"id":1609700,"known_for_department":"Writing","name":"Kim Rosenstock","original_name":"Kim Rosenstock","popularity":0.1457,"profile_path":"/prGRp5LUzNV8Gh7OvASAqH3KYkz.jpg","credit_id":"657851144bfa545d001ea959","department":"Production","job":"Executive Producer"},{"adult":false,"gender":1,"id":217587,"known_for_department":"Writing","name":"Leslye Headland","original_name":"Leslye Headland","popularity":0.2198,"profile_path":"/tHrxGDqAp89F9m0ISRUuuUeKrb4.jpg","credit_id":"6578512b2dc9dc013f80e540","department":"Production","job":"Executive Producer"},{"adult":false,"gender":1,"id":1364163,"known_for_department":"Production","name":"Katherine Pope","original_name":"Katherine Pope","popularity":0.0758,"profile_path":"/vWukVkkc4NPnuvkx34p1eH6trPt.jpg","credit_id":"6578513689d97f01009ed240","department":"Production","job":"Executive Producer"},{"adult":false,"gender":2,"id":2413434,"known_for_department":"Production","name":"Hernan Lopez","original_name":"Hernan Lopez","popularity":0.0882,"profile_path":"/umT9s3LClc0nxkau6FmMhmnCfBT.jpg","credit_id":"6578519089d97f01009ed250","department":"Production","job":"Executive Producer"},{"adult":false,"gender":2,"id":1222213,"known_for_department":"Production","name":"Aaron Hart","original_name":"Aaron Hart","popularity":0.0286,"profile_path":"/u6PFTb73ZxWTah89AUaehLmEdbC.jpg","credit_id":"657851997a3c5200ebfe4a9e","department":"Production","job":"Executive Producer"},{"adult":false,"gender":2,"id":81068,"known_for_department":"Writing","name":"Marshall Lewy","original_name":"Marshall Lewy","popularity":0.0853,"profile_path":"/8dGGAmVgaukqQpyfBYxXj29Ooa8.jpg","credit_id":"657851a5e93e95218dcc1869","department":"Production","job":"Executive Producer"},{"adult":false,"gender":1,"id":1226798,"known_for_department":"Acting","name":"Nikki Boyer","original_name":"Nikki Boyer","popularity":0.197,"profile_path":null,"credit_id":"657851fd564ec7011b208598","department":"Production","job":"Executive Producer"},{"adult":false,"gender":1,"id":3077301,"known_for_department":"Production","name":"Christina M. Fitzgerald","original_name":"Christina M. Fitzgerald","popularity":0.0688,"profile_path":null,"credit_id":"67ef8c83ede8d82f3bad0c99","department":"Production","job":"Producer"},{"adult":false,"gender":1,"id":4901,"known_for_department":"Production","name":"Kathy Ciric","original_name":"Kathy Ciric","popularity":0.1737,"profile_path":null,"credit_id":"67ef8cb7aa77e08af7993838","department":"Production","job":"Executive Producer"},{"adult":false,"gender":0,"id":5217904,"known_for_department":"Production","name":"Stephanie Jenz","original_name":"Stephanie Jenz","popularity":0,"profile_path":null,"credit_id":"67ef8cd1aa77e08af7993864","department":"Production","job":"Co-Executive Producer"},{"adult":false,"gender":1,"id":2035232,"known_for_department":"Directing","name":"Shannon Murphy","original_name":"Shannon Murphy","popularity":0.1238,"profile_path":"/vx2ESOt6od8iM4WA2DiVWfl9tzy.jpg","credit_id":"67ef8d012f7d437027993956","department":"Production","job":"Executive Producer"},{"adult":false,"gender":1,"id":1413536,"known_for_department":"Writing","name":"Sheila Callaghan","original_name":"Sheila Callaghan","popularity":0.2241,"profile_path":null,"credit_id":"67ef8d5548d6f031b0acf5d4","department":"Production","job":"Co-Executive Producer"},{"adult":false,"gender":1,"id":1812,"known_for_department":"Acting","name":"Michelle Williams","original_name":"Michelle Williams","popularity":3.1418,"profile_path":"/mfgKyigaQLI0NtZsaJRVlbUiMdX.jpg","credit_id":"67ef8d6c48d6f031b0acf5ff","department":"Production","job":"Executive Producer"},{"adult":false,"gender":0,"id":1416655,"known_for_department":"Writing","name":"Harris Danow","original_name":"Harris Danow","popularity":0.0672,"profile_path":null,"credit_id":"67ef8d8548d6f031b0acf603","department":"Production","job":"Co-Executive Producer"},{"adult":false,"gender":0,"id":3248143,"known_for_department":"Writing","name":"Madeleine George","original_name":"Madeleine George","popularity":0.0429,"profile_path":null,"credit_id":"67ef8d97a9313c7184ad0905","department":"Production","job":"Co-Producer"},{"adult":false,"gender":2,"id":1394652,"known_for_department":"Camera","name":"Chris Teague","original_name":"Chris Teague","popularity":0.0621,"profile_path":null,"credit_id":"67ef8dacede8d82f3bad0d0c","department":"Production","job":"Producer"},{"adult":false,"gender":1,"id":2026770,"known_for_department":"Sound","name":"Ariel Marx","original_name":"Ariel Marx","popularity":0.1336,"profile_path":"/jJ4q9Q10AgW7wRnvqB0IgLOIrtX.jpg","credit_id":"67ef8e1b2f7d43702799398f","department":"Sound","job":"Original Music Composer"},{"adult":false,"gender":1,"id":1089660,"known_for_department":"Production","name":"Jeanie Bacharach","original_name":"Jeanie Bacharach","popularity":0.0952,"profile_path":"/RvqGhgec4eSAZ0CxKLROgXo400.jpg","credit_id":"67ef8e8d2f7d4370279939c6","department":"Production","job":"Casting"},{"adult":false,"gender":0,"id":1155099,"known_for_department":"Art","name":"Michael Bricker","original_name":"Michael Bricker","popularity":0.0071,"profile_path":null,"credit_id":"67ef8eb2931ce174a2d92c1b","department":"Art","job":"Production Design"},{"adult":false,"gender":2,"id":4027052,"known_for_department":"Art","name":"John Duhigg Cox","original_name":"John Duhigg Cox","popularity":0.0338,"profile_path":null,"credit_id":"67ef8ec4cbd55b661fd920a0","department":"Art","job":"Art Direction"},{"adult":false,"gender":1,"id":1094563,"known_for_department":"Art","name":"Stephanie Q. Bowen","original_name":"Stephanie Q. Bowen","popularity":0.0541,"profile_path":null,"credit_id":"67ef8ed3cbd55b661fd920a6","department":"Art","job":"Set Decoration"},{"adult":false,"gender":1,"id":33439,"known_for_department":"Costume & Make-Up","name":"Melissa Toth","original_name":"Melissa Toth","popularity":0.207,"profile_path":"/2lJQri7Qk3KAcVpVCfrfiBSsAnW.jpg","credit_id":"67ef8ee12f7d437027993a12","department":"Costume & Make-Up","job":"Costume Design"},{"adult":false,"gender":1,"id":1528019,"known_for_department":"Costume & Make-Up","name":"Christine Hooghuis","original_name":"Christine Hooghuis","popularity":0.1034,"profile_path":null,"credit_id":"67ef8ef52f7d437027993a18","department":"Costume & Make-Up","job":"Makeup Artist"},{"adult":false,"gender":1,"id":1740249,"known_for_department":"Costume & Make-Up","name":"Jackie Risotto","original_name":"Jackie Risotto","popularity":0.0281,"profile_path":null,"credit_id":"67ef8f00f5a80aa545993507","department":"Costume & Make-Up","job":"Makeup Department Head"},{"adult":false,"gender":2,"id":1122265,"known_for_department":"Sound","name":"Martin Czembor","original_name":"Martin Czembor","popularity":0.0806,"profile_path":null,"credit_id":"67ef8f1c2f7d437027993a1c","department":"Sound","job":"Sound Re-Recording Mixer"},{"adult":false,"gender":2,"id":575691,"known_for_department":"Sound","name":"David Forshee","original_name":"David Forshee","popularity":0.0311,"profile_path":null,"credit_id":"67ef8f3648d6f031b0acf6a0","department":"Sound","job":"Sound Re-Recording Mixer"},{"adult":false,"gender":2,"id":1554998,"known_for_department":"Crew","name":"Cort Hessler","original_name":"Cort Hessler","popularity":0.2973,"profile_path":"/c6F1FPXob5qrahiWqceVVW0KXVK.jpg","credit_id":"67ef8f50931ce174a2d92cea","department":"Crew","job":"Stunt Coordinator"},{"adult":false,"gender":1,"id":4426022,"known_for_department":"Production","name":"Jen Sargent","original_name":"Jen Sargent","popularity":0.0589,"profile_path":"/awZtPlorUAWjWJ5NImtXbpcY4Qp.jpg","credit_id":"67f1a43be1d5c23c6ed92a4a","department":"Production","job":"Executive Producer"},{"adult":false,"gender":3,"id":3730831,"known_for_department":"Acting","name":"Sabrina Wu","original_name":"Sabrina Wu","popularity":0.2476,"profile_path":"/7yA3L0pYuO5MvKg82UXxo3KrFmp.jpg","credit_id":"67f6927dddf9194387da5f26","department":"Writing","job":"Story Editor"}],"id":241405},"media":{"videos":[{"iso_639_1":"en","iso_3166_1":"US","name":"Official Trailer","key":"B4WAcOJ5bvo","site":"YouTube","size":1080,"type":"Trailer","official":true,"published_at":"2025-03-18T15:29:48.000Z","id":"67d9d9983d25468231d4bb9c"},{"iso_639_1":"en","iso_3166_1":"US","name":"Teaser - No Regrets","key":"8BblHPrH6w4","site":"YouTube","size":1080,"type":"Teaser","official":true,"published_at":"2025-03-21T15:59:49.000Z","id":"67df47d4ce605a1ed1c6ff23"},{"iso_639_1":"en","iso_3166_1":"US","name":"Teaser - What Do You Fantasize About?","key":"sWIUFJZdOXM","site":"YouTube","size":1080,"type":"Teaser","official":true,"published_at":"2025-03-26T15:59:54.000Z","id":"67e4a6aeb8fc398996109bd7"},{"iso_639_1":"en","iso_3166_1":"US","name":"Teaser - Feel Alive","key":"xno2hSv_KiU","site":"YouTube","size":1080,"type":"Teaser","official":true,"published_at":"2025-03-29T15:59:53.000Z","id":"67e8dc8361cac2b3a3f6c4b9"},{"iso_639_1":"en","iso_3166_1":"US","name":"Teaser - Make It Sexy","key":"wN9-JCGtRMo","site":"YouTube","size":1080,"type":"Teaser","official":true,"published_at":"2025-04-01T23:37:51.000Z","id":"67ece1213d8e74e518012341"}],"backdrops":[{"aspect_ratio":1.778,"height":889,"iso_639_1":null,"file_path":"/1ygwQw1Jf8s9Q4fx2Rym7DccRBQ.jpg","vote_average":6.722,"vote_count":6,"width":1581},{"aspect_ratio":1.778,"height":2160,"iso_639_1":null,"file_path":"/bVgcsQddGZ71kTXGrFJOn1fDEZj.jpg","vote_average":4.884,"vote_count":13,"width":3840},{"aspect_ratio":1.778,"height":2160,"iso_639_1":"en","file_path":"/3PW5PVANpes8KmPFQmMxwNVJbE8.jpg","vote_average":3.334,"vote_count":1,"width":3840},{"aspect_ratio":1.778,"height":900,"iso_639_1":null,"file_path":"/pYoTZVdT7mC3sHxgp86r2Ox1RZa.jpg","vote_average":3.334,"vote_count":1,"width":1600},{"aspect_ratio":1.778,"height":1440,"iso_639_1":null,"file_path":"/AociJJzKVSuCnpVGfiRp2lWJxLU.jpg","vote_average":1.31,"vote_count":7,"width":2560},{"aspect_ratio":1.778,"height":2160,"iso_639_1":null,"file_path":"/wWcCUMOHfUCpZeR3zsNQSTJskOU.jpg","vote_average":1.208,"vote_count":8,"width":3840},{"aspect_ratio":1.778,"height":2160,"iso_639_1":null,"file_path":"/1H9K2yHtWxo7pplDgewsHYakZzg.jpg","vote_average":1.208,"vote_count":8,"width":3840},{"aspect_ratio":1.778,"height":2160,"iso_639_1":null,"file_path":"/qkoYaPxHziSrck5exatMhg2GHUw.jpg","vote_average":0.166,"vote_count":3,"width":3840},{"aspect_ratio":1.778,"height":2160,"iso_639_1":null,"file_path":"/2nuSpT6bLgLXtTVsdSgVcoR5XE5.jpg","vote_average":0.166,"vote_count":2,"width":3840},{"aspect_ratio":1.778,"height":2160,"iso_639_1":"en","file_path":"/hArQO6naCLihhUQBoQhmcPHC0Tz.jpg","vote_average":0.166,"vote_count":1,"width":3840},{"aspect_ratio":1.778,"height":1080,"iso_639_1":"he","file_path":"/utJTIWOZvGIZdtIsS5db7g3iRxT.jpg","vote_average":0,"vote_count":0,"width":1920},{"aspect_ratio":1.778,"height":2160,"iso_639_1":"uk","file_path":"/oSKEsiVIEGPYDMfH04VLFvWDYRk.jpg","vote_average":0,"vote_count":0,"width":3840},{"aspect_ratio":1.778,"height":2160,"iso_639_1":"cs","file_path":"/fcO4w1Sh1amjSXIdB7ar85i7rDi.jpg","vote_average":0,"vote_count":0,"width":3840},{"aspect_ratio":1.778,"height":2160,"iso_639_1":"es","file_path":"/gQUqwabNLNlxWlJWAET62HKWloO.jpg","vote_average":0,"vote_count":0,"width":3840},{"aspect_ratio":1.778,"height":2160,"iso_639_1":"zh","file_path":"/2iMaMTSwDQnwwTdr2PYBcH5yfzL.jpg","vote_average":0,"vote_count":0,"width":3840},{"aspect_ratio":1.778,"height":2160,"iso_639_1":"pl","file_path":"/cGURwzGtKa6czimda1x2O3GMl27.jpg","vote_average":0,"vote_count":0,"width":3840},{"aspect_ratio":1.778,"height":2160,"iso_639_1":"sk","file_path":"/m63JYgAYhiLFhbVl3gXARi7hwXM.jpg","vote_average":0,"vote_count":0,"width":3840},{"aspect_ratio":1.778,"height":2160,"iso_639_1":"pt","file_path":"/1JLksxu19P0BXI88yhnqEswvFpP.jpg","vote_average":0,"vote_count":0,"width":3840},{"aspect_ratio":1.778,"height":2160,"iso_639_1":"en","file_path":"/1ziDHCVMDfdAJQPibcwo9Pv3Hzc.jpg","vote_average":0,"vote_count":0,"width":3840},{"aspect_ratio":1.778,"height":2160,"iso_639_1":"hu","file_path":"/fx0AK9DaoY8GKn2pH8s3ngbCwkK.jpg","vote_average":0,"vote_count":0,"width":3840},{"aspect_ratio":1.778,"height":2160,"iso_639_1":"ro","file_path":"/xBWptSVO4Q29xcGdyAtdotDsQXa.jpg","vote_average":0,"vote_count":0,"width":3840},{"aspect_ratio":1.778,"height":2160,"iso_639_1":"ja","file_path":"/49CDcLBVamlQ1ORC3Xa8S48N2Q0.jpg","vote_average":0,"vote_count":0,"width":3840},{"aspect_ratio":1.778,"height":2160,"iso_639_1":"ko","file_path":"/pJsgMXsUBWACT7O5Oqs6OHVrOqD.jpg","vote_average":0,"vote_count":0,"width":3840},{"aspect_ratio":1.779,"height":890,"iso_639_1":null,"file_path":"/1TwLYO0h4d4ah0oFTG5BN5AmAjh.jpg","vote_average":0,"vote_count":0,"width":1583},{"aspect_ratio":1.778,"height":765,"iso_639_1":null,"file_path":"/f0ViqbWaHjPmsUtuINcALnBPWCv.jpg","vote_average":0,"vote_count":0,"width":1360},{"aspect_ratio":1.778,"height":1406,"iso_639_1":null,"file_path":"/hPmaX9pvfwKPatrS5UzW5oC4V2u.jpg","vote_average":0,"vote_count":0,"width":2500},{"aspect_ratio":1.778,"height":1080,"iso_639_1":null,"file_path":"/uuEo4J7b3YALBXsYqEFZgdz7doA.jpg","vote_average":0,"vote_count":0,"width":1920}],"posters":[{"aspect_ratio":0.667,"height":1500,"iso_639_1":"en","file_path":"/xaKb3cTh8mT6fgLSXuqo4JoS0dU.jpg","vote_average":10,"vote_count":5,"width":1000},{"aspect_ratio":0.667,"height":3000,"iso_639_1":"pt","file_path":"/egbPLdcEGJPteodzWGiiWjXENJU.jpg","vote_average":3.334,"vote_count":1,"width":2000},{"aspect_ratio":0.667,"height":1500,"iso_639_1":"he","file_path":"/jI8U8TmgkuFxD7ZFudmdzSAdUeJ.jpg","vote_average":3.334,"vote_count":1,"width":1000},{"aspect_ratio":0.667,"height":3000,"iso_639_1":"en","file_path":"/nnNCdELLF9f9CZKMJDbuULgXJeO.jpg","vote_average":3.334,"vote_count":2,"width":2000},{"aspect_ratio":0.667,"height":3000,"iso_639_1":"en","file_path":"/xGi8TogE5SGudRq0PXwH3p50HBn.jpg","vote_average":3.334,"vote_count":1,"width":2000},{"aspect_ratio":0.667,"height":3000,"iso_639_1":"pt","file_path":"/hj98rbPCW9Opc0VPqmUHD0pO6xO.jpg","vote_average":2.278,"vote_count":3,"width":2000},{"aspect_ratio":0.667,"height":2880,"iso_639_1":"he","file_path":"/2dNlGquCaAHKpRvlCXNXJJD5W3O.jpg","vote_average":1.75,"vote_count":2,"width":1920},{"aspect_ratio":0.667,"height":3000,"iso_639_1":"pt","file_path":"/fHGa2D9PBSAqBkb4xJm6wSMD8Yi.jpg","vote_average":1.75,"vote_count":1,"width":2000},{"aspect_ratio":0.667,"height":1350,"iso_639_1":"en","file_path":"/7rpJEjzwlxn84yTt1LdlwIrG0JJ.jpg","vote_average":0.166,"vote_count":4,"width":900},{"aspect_ratio":0.667,"height":1500,"iso_639_1":"en","file_path":"/vl1cKBtop9blJDSo6FE6iwjpHEx.jpg","vote_average":0.166,"vote_count":2,"width":1000},{"aspect_ratio":0.667,"height":3000,"iso_639_1":"en","file_path":"/2qxnYlxVqXOMVRMeno6jzBz1Ldn.jpg","vote_average":0.166,"vote_count":1,"width":2000},{"aspect_ratio":0.667,"height":2160,"iso_639_1":null,"file_path":"/pjIODKHTnX2PkBj0N3Zzb7jEbAh.jpg","vote_average":0,"vote_count":0,"width":1440},{"aspect_ratio":0.667,"height":2880,"iso_639_1":null,"file_path":"/9e5IGEWLUVz0YWF55oSlsYIwjmL.jpg","vote_average":0,"vote_count":0,"width":1920},{"aspect_ratio":0.667,"height":2880,"iso_639_1":"en","file_path":"/zmYOx8eR4ikUHJyUZ7qvhwIo1Cf.jpg","vote_average":0,"vote_count":0,"width":1920},{"aspect_ratio":0.667,"height":3000,"iso_639_1":null,"file_path":"/uckfy3r6GsLUuonE9LeWHldkIu3.jpg","vote_average":0,"vote_count":0,"width":2000},{"aspect_ratio":0.667,"height":3000,"iso_639_1":null,"file_path":"/o11dQhK2ebFWblQvbRhzB2gsVET.jpg","vote_average":0,"vote_count":0,"width":2000},{"aspect_ratio":0.667,"height":1532,"iso_639_1":"he","file_path":"/wqhBpTVnSxJMkI8hTHxOoOMyFEK.jpg","vote_average":0,"vote_count":0,"width":1022},{"aspect_ratio":0.667,"height":3000,"iso_639_1":"uk","file_path":"/haYFH3dfCG4zPWyirNyrRSNiHuo.jpg","vote_average":0,"vote_count":0,"width":2000},{"aspect_ratio":0.667,"height":3000,"iso_639_1":"uk","file_path":"/kkuYCTlTcrYLxT7mf9QOQPtnwQO.jpg","vote_average":0,"vote_count":0,"width":2000},{"aspect_ratio":0.667,"height":2880,"iso_639_1":"nl","file_path":"/pVyv9lsIS7ioo1W8ml122OU6SlQ.jpg","vote_average":0,"vote_count":0,"width":1920},{"aspect_ratio":0.667,"height":3000,"iso_639_1":"en","file_path":"/xvclvaWFPJww3cfOs90Vk1niz4o.jpg","vote_average":0,"vote_count":0,"width":2000},{"aspect_ratio":0.667,"height":3000,"iso_639_1":"en","file_path":"/avcim8zKdxJ0bt91Nl7Oe4aFStM.jpg","vote_average":0,"vote_count":1,"width":2000},{"aspect_ratio":0.667,"height":3000,"iso_639_1":"cs","file_path":"/jKtmOnMx6XibS4ispof2CZ05jLc.jpg","vote_average":0,"vote_count":0,"width":2000},{"aspect_ratio":0.667,"height":3000,"iso_639_1":"pl","file_path":"/5ib5aLaxw2FwLHp6sft3jKSp2MK.jpg","vote_average":0,"vote_count":0,"width":2000},{"aspect_ratio":0.667,"height":3000,"iso_639_1":"ja","file_path":"/ivbzzc1IqN5VNPNv5ctlFeWKfYy.jpg","vote_average":0,"vote_count":0,"width":2000},{"aspect_ratio":0.667,"height":3000,"iso_639_1":"es","file_path":"/uuMHxOyzEFjW5tyZmoDos0hfZQH.jpg","vote_average":0,"vote_count":0,"width":2000},{"aspect_ratio":0.667,"height":3000,"iso_639_1":"zh","file_path":"/u2d8z7S4xO5TQ06qxghcZpIr1Rh.jpg","vote_average":0,"vote_count":0,"width":2000},{"aspect_ratio":0.667,"height":3000,"iso_639_1":"ko","file_path":"/ibfxRoq3BQAFXTxMSz7yXY5qY99.jpg","vote_average":0,"vote_count":0,"width":2000},{"aspect_ratio":0.667,"height":3000,"iso_639_1":"sk","file_path":"/eMvqHSiLPNurAR1AVFQ2IPCBDHk.jpg","vote_average":0,"vote_count":0,"width":2000},{"aspect_ratio":0.667,"height":3000,"iso_639_1":"ro","file_path":"/9luInR8cFONvIx5DhCqjUS5qE9e.jpg","vote_average":0,"vote_count":0,"width":2000},{"aspect_ratio":0.667,"height":3000,"iso_639_1":"hu","file_path":"/7iWR0mcNQLc9RLjpKGJMzl4PzPI.jpg","vote_average":0,"vote_count":0,"width":2000},{"aspect_ratio":0.667,"height":3000,"iso_639_1":"ru","file_path":"/g4fFQyQ93SezQRBvrzwc9UJWrr8.jpg","vote_average":0,"vote_count":0,"width":2000}]},"externalIds":{"id":241405,"imdb_id":"tt30252752","freebase_mid":null,"freebase_id":null,"tvdb_id":442867,"tvrage_id":null,"wikidata_id":"Q125726745","facebook_id":null,"instagram_id":null,"twitter_id":null},"reviews":[],"recommendations":[{"backdrop_path":"/dDx7bjxtJcMwUhowCn7VhPwLEzp.jpg","id":233256,"name":"The Stolen Girl","original_name":"The Stolen Girl","overview":"A mother-of-two has her world turned upside down when she agrees to let her nine-year-old daughter have a sleepover at her new best friend's house.","poster_path":"/dukqZNsr9vlzfAEa8xAABRT3yxD.jpg","media_type":"tv","adult":false,"original_language":"en","genre_ids":[18,9648],"popularity":52.6981,"first_air_date":"2025-04-16","vote_average":6.36,"vote_count":25,"origin_country":["GB"]},{"backdrop_path":"/yoImho3EUrbwU4RrUlRfCrN6Mqc.jpg","id":17627,"name":"The Take","original_name":"The Take","overview":"Freddie Jackson is released from prison in 1984 having served a four-year sentence for armed robbery. His wife Jackie, who has been waiting for him on the outside in the mistaken belief that that he wants to go straight, soon finds herself disappointed: Freddie is in fact raring to get back into the game and has set his sights on becoming top dog in the East End underworld.","poster_path":"/1caD6qD3acG2NmVnZeH0xibcfT4.jpg","media_type":"tv","adult":false,"original_language":"en","genre_ids":[10759,18],"popularity":2.409,"first_air_date":"2009-06-17","vote_average":7.533,"vote_count":75,"origin_country":["GB"]},{"backdrop_path":"/kOcTSsKjC1h9Ez8l7yzKPZ4XF9t.jpg","id":278704,"name":"Mobile Suit Gundam GQuuuuuuX","original_name":"機動戦士Gundam GQuuuuuuX（ジークアクス）","overview":"High-school student Amate Yuzuriha lives peacefully in a space colony floating in outer space. But when she meets a war refugee named Nyaan, Amate is drawn into the illegal mobile suit dueling sport known as Clan Battle.","poster_path":"/jb5d4vqHmKSQh9rB2T394e3z5To.jpg","media_type":"tv","adult":false,"original_language":"ja","genre_ids":[16,10759,10765,18],"popularity":18.0058,"first_air_date":"2025-04-09","vote_average":8.6,"vote_count":7,"origin_country":["JP"]},{"backdrop_path":"/tQqbbxBAdW2ql8vbOqMOJbtSQ7O.jpg","id":247718,"name":"MobLand","original_name":"MobLand","overview":"Two mob families clash in a war that threatens to topple empires and lives.","poster_path":"/f7fMjGQD2sK3qBmJRZlvbKvjTr2.jpg","media_type":"tv","adult":false,"original_language":"en","genre_ids":[80,18],"popularity":42.5279,"first_air_date":"2025-03-30","vote_average":8.4,"vote_count":69,"origin_country":["GB","US"]},{"backdrop_path":"/n3qhrNE6oHFyfDgTYXbiju7jIbm.jpg","id":259288,"name":"Friendly Rivalry","original_name":"선의의 경쟁","overview":"A high-teen mystery thriller about a close relationship between teenage girls in a harsher survival competition than entrance examinations.","poster_path":"/eRwNhjpizV7up8KrCmiI94is1bl.jpg","media_type":"tv","adult":false,"original_language":"ko","genre_ids":[9648,18],"popularity":10.2658,"first_air_date":"2025-02-10","vote_average":8.809,"vote_count":47,"origin_country":["KR"]},{"backdrop_path":"/erJMfbBfhasNw6gKpp8D1llxmPu.jpg","id":114500,"name":"Win or Lose","original_name":"Win or Lose","overview":"As a championship game looms, eight characters are thrown a curveball in their off-the-field lives.","poster_path":"/rnVVkTU8noAZshs1sHdkxdGcVIP.jpg","media_type":"tv","adult":false,"original_language":"en","genre_ids":[16,18,10751,35],"popularity":8.5723,"first_air_date":"2025-02-19","vote_average":8.1,"vote_count":93,"origin_country":["US"]},{"backdrop_path":"/z3BkMbCy5ajZPMyKEUwsPHuz2cV.jpg","id":250307,"name":"The Pitt","original_name":"The Pitt","overview":"The staff of Pittsburgh's Trauma Medical Center work around the clock to save lives in an overcrowded and underfunded emergency department.","poster_path":"/6fMGktEDXMZZPACJ5cWkVQ6TSte.jpg","media_type":"tv","adult":false,"original_language":"en","genre_ids":[18],"popularity":30.8851,"first_air_date":"2025-01-09","vote_average":8.6,"vote_count":127,"origin_country":["US"]},{"backdrop_path":"/o2F0cIIuEOuai7Vzv0Rh7YvRppT.jpg","id":4386,"name":"Baywatch","original_name":"Baywatch","overview":"Join the Baywatch lifeguards on their thrilling adventures filled with beautiful beaches and those iconic red swimsuits.","poster_path":"/34t8WxHn1OcIVpcTxmjYmjX9tE4.jpg","media_type":"tv","adult":false,"original_language":"en","genre_ids":[10759,18,80],"popularity":56.1857,"first_air_date":"1989-04-23","vote_average":5.943,"vote_count":491,"origin_country":["US"]},{"backdrop_path":"/hrsRczdsAHBLTDzlIqt82bxY0Tt.jpg","id":202555,"name":"Daredevil: Born Again","original_name":"Daredevil: Born Again","overview":"Matt Murdock, a blind lawyer with heightened abilities, is fighting for justice through his bustling law firm, while former mob boss Wilson Fisk pursues his own political endeavors in New York. When their past identities begin to emerge, both men find themselves on an inevitable collision course.","poster_path":"/9lLuhV703HGCbnz6FxnqCwIwzAZ.jpg","media_type":"tv","adult":false,"original_language":"en","genre_ids":[18,80],"popularity":84.3221,"first_air_date":"2025-03-04","vote_average":8.1,"vote_count":369,"origin_country":["US"]},{"backdrop_path":"/1DmAeDIAN6nvVpgTqiurDPUwuj7.jpg","id":97175,"name":"Fate: The Winx Saga","original_name":"Fate: The Winx Saga","overview":"The coming-of-age journey of five fairies attending Alfea, a magical boarding school in the Otherworld where they must learn to master their powers while navigating love, rivalries, and the monsters that threaten their very existence.","poster_path":"/oHj6guMrLfQcBzo3uxwBJc8Y736.jpg","media_type":"tv","adult":false,"original_language":"en","genre_ids":[10765,18],"popularity":9.3938,"first_air_date":"2021-01-22","vote_average":8.023,"vote_count":1465,"origin_country":["GB"]},{"backdrop_path":"/9SUiZcIuDa8SxwrDsjtm1JEgjR4.jpg","id":249042,"name":"Adolescence","original_name":"Adolescence","overview":"When a 13-year-old is accused of the murder of a classmate, his family, therapist and the detective in charge are all left asking: what really happened?","poster_path":"/tDHWWReefmOOjBCJZUck8cNwssk.jpg","media_type":"tv","adult":false,"original_language":"en","genre_ids":[18,80],"popularity":53.3448,"first_air_date":"2025-03-13","vote_average":7.849,"vote_count":813,"origin_country":["GB","US"]},{"backdrop_path":"/a4doyPOabvQor0RGkWdhVENAR3G.jpg","id":1413,"name":"American Horror Story","original_name":"American Horror Story","overview":"An anthology horror drama series centering on different characters and locations, including a house with a murderous past, an asylum, a witch coven, a freak show, a hotel, a farmhouse in Roanoke, a cult, the apocalypse and a summer camp.","poster_path":"/5LLG9bjq0i7V5N4UfRhnab8zHK4.jpg","media_type":"tv","adult":false,"original_language":"en","genre_ids":[18,9648,10765],"popularity":47.0864,"first_air_date":"2011-10-05","vote_average":8.1,"vote_count":5732,"origin_country":["US"]},{"backdrop_path":"/9faGSFi5jam6pDWGNd0p8JcJgXQ.jpg","id":1396,"name":"Breaking Bad","original_name":"Breaking Bad","overview":"Walter White, a New Mexico chemistry teacher, is diagnosed with Stage III cancer and given a prognosis of only two years left to live. He becomes filled with a sense of fearlessness and an unrelenting desire to secure his family's financial future at any cost as he enters the dangerous world of drugs and crime.","poster_path":"/ineLOBPG8AZsluYwnkMpHRyu7L.jpg","media_type":"tv","adult":false,"original_language":"en","genre_ids":[18,80],"popularity":126.2781,"first_air_date":"2008-01-20","vote_average":8.9,"vote_count":15458,"origin_country":["US"]},{"backdrop_path":"/u23G9KZregWHs1use6ir1fX27gl.jpg","id":81356,"name":"Sex Education","original_name":"Sex Education","overview":"Inexperienced Otis channels his sex therapist mom when he teams up with rebellious Maeve to set up an underground sex therapy clinic at school.","poster_path":"/bc3bmTdnoKcRuO9xdQKgAbB7Y9Z.jpg","media_type":"tv","adult":false,"original_language":"en","genre_ids":[35,18],"popularity":48.4717,"first_air_date":"2019-01-11","vote_average":8.237,"vote_count":7457,"origin_country":["GB"]},{"backdrop_path":"/zZqpAXxVSBtxV9qPBcscfXBcL2w.jpg","id":1399,"name":"Game of Thrones","original_name":"Game of Thrones","overview":"Seven noble families fight for control of the mythical land of Westeros. Friction between the houses leads to full-scale war. All while a very ancient evil awakens in the farthest north. Amidst the war, a neglected military order of misfits, the Night's Watch, is all that stands between the realms of men and icy horrors beyond.","poster_path":"/1XS1oqL89opfnbLl8WnZY1O1uJx.jpg","media_type":"tv","adult":false,"original_language":"en","genre_ids":[10765,18,10759],"popularity":189.105,"first_air_date":"2011-04-17","vote_average":8.457,"vote_count":24918,"origin_country":["US"]},{"backdrop_path":"/l0qVZIpXtIo7km9u5Yqh0nKPOr5.jpg","id":1668,"name":"Friends","original_name":"Friends","overview":"Six young people from New York City, on their own and struggling to survive in the real world, find the companionship, comfort and support they get from each other to be the perfect antidote to the pressures of life.","poster_path":"/2koX1xLkpTQM4IZebYvKysFW1Nh.jpg","media_type":"tv","adult":false,"original_language":"en","genre_ids":[35],"popularity":121.792,"first_air_date":"1994-09-22","vote_average":8.4,"vote_count":8341,"origin_country":["US"]},{"backdrop_path":"/pxeqQX4qFQ0cVxPt5SWZENV5BH3.jpg","id":456,"name":"The Simpsons","original_name":"The Simpsons","overview":"Set in Springfield, the average American town, the show focuses on the antics and everyday adventures of the Simpson family; Homer, Marge, Bart, Lisa and Maggie, as well as a virtual cast of thousands. Since the beginning, the series has been a pop culture icon, attracting hundreds of celebrities to guest star. The show has also made name for itself in its fearless satirical take on politics, media and American life in general.","poster_path":"/vHqeLzYl3dEAutojCO26g0LIkom.jpg","media_type":"tv","adult":false,"original_language":"en","genre_ids":[10751,16,35],"popularity":201.5099,"first_air_date":"1989-12-17","vote_average":8.016,"vote_count":10170,"origin_country":["US"]},{"backdrop_path":"/rAOjnEFTuNysY7bot8zonhImGMh.jpg","id":1402,"name":"The Walking Dead","original_name":"The Walking Dead","overview":"Sheriff's deputy Rick Grimes awakens from a coma to find a post-apocalyptic world dominated by flesh-eating zombies. He sets out to find his family and encounters many other survivors along the way.","poster_path":"/ng3cMtxYKt1OSQYqFlnKWnVsqNO.jpg","media_type":"tv","adult":false,"original_language":"en","genre_ids":[10759,18,10765],"popularity":111.4854,"first_air_date":"2010-10-31","vote_average":8.099,"vote_count":16920,"origin_country":["US"]},{"backdrop_path":"/ukewRnKD05Si7DkED2tSKBTXeEd.jpg","id":84773,"name":"The Lord of the Rings: The Rings of Power","original_name":"The Lord of the Rings: The Rings of Power","overview":"Beginning in a time of relative peace, we follow an ensemble cast of characters as they confront the re-emergence of evil to Middle-earth. From the darkest depths of the Misty Mountains, to the majestic forests of Lindon, to the breathtaking island kingdom of Númenor, to the furthest reaches of the map, these kingdoms and characters will carve out legacies that live on long after they are gone.","poster_path":"/mYLOqiStMxDK3fYZFirgrMt8z5d.jpg","media_type":"tv","adult":false,"original_language":"en","genre_ids":[10759,10765,18],"popularity":67.9721,"first_air_date":"2022-09-01","vote_average":7.293,"vote_count":3284,"origin_country":["US"]},{"backdrop_path":"/7dowXHcFccjmxf0YZYxDFkfVq65.jpg","id":100088,"name":"The Last of Us","original_name":"The Last of Us","overview":"Twenty years after modern civilization has been destroyed, Joel, a hardened survivor, is hired to smuggle Ellie, a 14-year-old girl, out of an oppressive quarantine zone. What starts as a small job soon becomes a brutal, heartbreaking journey, as they both must traverse the United States and depend on each other for survival.","poster_path":"/dmo6TYuuJgaYinXBPjrgG9mB5od.jpg","media_type":"tv","adult":false,"original_language":"en","genre_ids":[18],"popularity":433.6105,"first_air_date":"2023-01-15","vote_average":8.578,"vote_count":5748,"origin_country":["US"]}]}